setup.py
pagepress/__init__.py
pagepress/command.py
pagepress/fixed_datetime.py
pagepress/generator.py
pagepress/page.py
pagepress/parsers.py
pagepress.egg-info/PKG-INFO
pagepress.egg-info/SOURCES.txt
pagepress.egg-info/dependency_links.txt
pagepress.egg-info/entry_points.txt
pagepress.egg-info/requires.txt
pagepress.egg-info/top_level.txt
pagepress.egg-info/zip-safe