Metadata-Version: 1.0
Name: pagepress
Version: 0.1
Summary: Pagepress is a Site-Generation Utility.
Home-page: http://iwill.id.au/pagepress/
Author: William Wheatley
Author-email: will@iwill.id.au
License: BSD
Keywords: blog html website
Platform: UNKNOWN
